gics/__init__.py
gics/definitions/__init__.py
gics/definitions/d_20140228.py
gics/definitions/d_20160901.py
gics/definitions/d_20180929.py
gics/definitions/d_20230318.py
gics/gics.py
gics/map.py
gics-0.2.1.dist-info/LICENSE
gics-0.2.1.dist-info/METADATA
gics-0.2.1.dist-info/WHEEL
gics-0.2.1.dist-info/RECORD
