Metadata-Version: 2.1
Name: gics
Version: 0.2.1
Summary: This library provides a way to parse, manipulate and analyze GICS codes.
License: MIT
Author: dorklein
Author-email: dorklein2@gmail.com
Requires-Python: >=3.7,<4.0
Classifier: License :: OSI Approved :: MIT License
Classifier: Programming Language :: Python :: 3
Classifier: Programming Language :: Python :: 3.7
Classifier: Programming Language :: Python :: 3.8
Classifier: Programming Language :: Python :: 3.9
Classifier: Programming Language :: Python :: 3.10
Classifier: Programming Language :: Python :: 3.11
Classifier: Programming Language :: Python :: 3.12
